actions_latest_mcp/__init__.py
actions_latest_mcp/__main__.py
actions_latest_mcp/server.py
actions_latest_mcp-0.1.1.dist-info/licenses/LICENSE
actions_latest_mcp-0.1.1.dist-info/METADATA
actions_latest_mcp-0.1.1.dist-info/WHEEL
actions_latest_mcp-0.1.1.dist-info/entry_points.txt
actions_latest_mcp-0.1.1.dist-info/top_level.txt
actions_latest_mcp-0.1.1.dist-info/RECORD
