Metadata-Version: 2.4
Name: actions-latest-mcp
Version: 0.1.1
Summary: MCP server to fetch GitHub Actions versions from actions-latest
Author: Hiosdra
License: GPL-3.0-or-later
Project-URL: Homepage, https://github.com/Hiosdra/actions-latest-mcp
Project-URL: Repository, https://github.com/Hiosdra/actions-latest-mcp
Project-URL: Issues, https://github.com/Hiosdra/actions-latest-mcp/issues
Keywords: mcp,github-actions,model-context-protocol
Classifier: Development Status :: 4 - Beta
Classifier: Intended Audience :: Developers
Classifier: Programming Language :: Python :: 3
Classifier: Programming Language :: Python :: 3.10
Classifier: Programming Language :: Python :: 3.11
Classifier: Programming Language :: Python :: 3.12
Requires-Python: >=3.10
License-File: LICENSE
Requires-Dist: mcp>=1.0.0
Requires-Dist: httpx>=0.27.0
Dynamic: license-file
